msc2/__init__.py
msc2/msc.py
minesc-0.1.7.dist-info/METADATA
minesc-0.1.7.dist-info/WHEEL
minesc-0.1.7.dist-info/top_level.txt
minesc-0.1.7.dist-info/RECORD
