Metadata-Version: 2.4
Name: minesc
Version: 0.1.7
Summary: Biblioteca pessoal pra facilitar minha vida
Home-page: https://github.com/aaaa560/Mine-Server-Manager-2
Author: Decaptado
Requires-Python: >=3.10
Requires-Dist: batata-lib==0.1.8
Requires-Dist: nkv==0.1
Dynamic: author
Dynamic: home-page
Dynamic: requires-dist
Dynamic: requires-python
Dynamic: summary
